pypigeonhole_simple_utils/__init__.py
pypigeonhole_simple_utils/app_setup.py
pypigeonhole_simple_utils/extra/__init__.py
pypigeonhole_simple_utils/extra/ftp_client.py
pypigeonhole_simple_utils/extra/http_client.py
pypigeonhole_simple_utils/extra/simple_encryption.py
pypigeonhole_simple_utils/extra/simple_yaml.py
pypigeonhole_simple_utils/extra/ssh_client.py
pypigeonhole_simple_utils/simple/__init__.py
pypigeonhole_simple_utils/simple/network_utils.py
pypigeonhole_simple_utils/simple/simple_data.py
pypigeonhole_simple_utils/simple/simple_email.py
pypigeonhole_simple_utils/simple/simple_filesystem.py
pypigeonhole_simple_utils/simple/simple_log.py
pypigeonhole_simple_utils/simple/simple_shell.py
pypigeonhole_simple_utils/simple/simple_str.py
pypigeonhole_simple_utils/simple/simple_timer.py
pypigeonhole_simple_utils-0.0.4.dist-info/LICENSE.md
pypigeonhole_simple_utils-0.0.4.dist-info/METADATA
pypigeonhole_simple_utils-0.0.4.dist-info/WHEEL
pypigeonhole_simple_utils-0.0.4.dist-info/top_level.txt
pypigeonhole_simple_utils-0.0.4.dist-info/RECORD
