Metadata-Version: 2.1
Name: pypigeonhole-simple-utils
Version: 0.0.4
Summary: Python Simple Utilities
Home-page: https://github.com/psilons/pypigeonhole-simple-utils
Author: psilons
Author-email: psilons.quanta@gmail.com
License: MIT
Platform: UNKNOWN
Requires-Python: >=3.6
